{
    "type": "Feature",
    "stac_version": "1.0.0",
    "stac_extensions": [
        "https://stac-extensions.github.io/ml-model/v1.0.0/schema.json"
    ],
    "id": "stac-generation",
    "collection": "ml-models",
    "geometry": "null",
    "properties": {
        "title": "STAC-generation",
        "description": "Issue per provare la generazione di file JSON - STAC",
        "main-category": "Machine Learning",
        "datetime": "2023-06-14T01:08:32Z",
        "keywords": [
            "classification",
            "decision-tree",
            "azure",
            "scikit-learn",
            "windows"
        ],
        "platform": [
            "Microsoft Azure"
        ],
        "framework": [
            "Scikit-learn",
            "Numpy"
        ],
        "algorithm": "Decision-Tree-Classifier",
        "license": "MIT",
        "ml-model:type": "ml-model",
        "ml-model:learning_approach": "supervised",
        "ml-model:prediction_type": [
            "classification"
        ],
        "ml-model:architecture": "decision-tree",
        "ml-model:training-processor-type": "cpu",
        "ml-model:training-os": "windows",
        "use-constraints": "no Constraint of Use"
    },
    "links": [
        {
            "rel": "root",
            "href": "./collection.json",
            "type": "application/json",
            "title": "Root Catalog"
        },
        {
            "rel": "parent",
            "href": "./collection.json",
            "type": "application/json",
            "title": "Root Catalog"
        },
        {
            "rel": "collection",
            "href": "./collection.json",
            "type": "application/json"
        },
        {
            "href": "www.prova.com",
            "rel": "about",
            "type": "text/html",
            "title": "Reference link"
        },
        {
            "href": "www.example.com",
            "rel": "about",
            "type": "text/html",
            "title": "Example"
        }
    ],
    "assets": {
        "input-data-used-1": {
            "href": "Link1",
            "type": "application/json",
            "title": "Input data used",
            "description": "Characteristics of the Link-1",
            "roles": [
                "data"
            ]
        },
        "input-data-used-2": {
            "href": "Link2",
            "type": "application/json",
            "title": "Input data used",
            "description": "Characteristics of the Link-2",
            "roles": [
                "data"
            ]
        },
        "model-checkpoint": {
            "href": "Link-1 to model 1",
            "type": "application/octet-stream",
            "title": "Model",
            "description": "Characteristics of the model in the link1",
            "performance": "97% accuracy",
            "roles": [
                "ml-model:checkpoint"
            ]
        }
    }
}